google_takeout_to_sqlite/__init__.py
google_takeout_to_sqlite/cli.py
google_takeout_to_sqlite/utils.py
google_takeout_to_sqlite-0.2.dist-info/LICENSE
google_takeout_to_sqlite-0.2.dist-info/METADATA
google_takeout_to_sqlite-0.2.dist-info/WHEEL
google_takeout_to_sqlite-0.2.dist-info/entry_points.txt
google_takeout_to_sqlite-0.2.dist-info/top_level.txt
google_takeout_to_sqlite-0.2.dist-info/RECORD
