Metadata-Version: 2.1
Name: google-takeout-to-sqlite
Version: 0.2
Summary: Save data from Google Takeout to a SQLite database
Home-page: https://github.com/dogsheep/google-takeout-to-sqlite
Author: Simon Willison
License: Apache License, Version 2.0
Platform: UNKNOWN
Requires-Dist: sqlite-utils (~=1.11)
Provides-Extra: test
Requires-Dist: pytest ; extra == 'test'
